mini_gpr/__init__.py
mini_gpr/kernels.py
mini_gpr/models.py
mini_gpr/opt.py
mini_gpr/solvers.py
mini_gpr/tutorials.py
mini_gpr/utils.py
mini_gpr/viz.py
mini_gpr-0.0.0.dist-info/METADATA
mini_gpr-0.0.0.dist-info/WHEEL
mini_gpr-0.0.0.dist-info/RECORD
