Metadata-Version: 2.4
Name: mini-gpr
Version: 0.0.0
Summary: a minimal reference implementation of gaussian process regression in pure numpy
Author-email: John Gardner <gardner.john97+dphil@gmail.com>
Requires-Python: >=3.11
Requires-Dist: jaxtyping>=0.3.2
Requires-Dist: matplotlib>=3.10.3
Requires-Dist: numpy>=2.3.0
